{
  "generatedAt": "2025-11-11T04:48:09.742Z",
  "sources": {
    "nflNextGame": "The Odds API (h2h)",
    "nflFutures": "ESPN futures (auto-discovered; de-vigged)",
    "nflCurrentOU": "Covers.com win totals (scraped HTML)"
  },
  "nflNextGame": [
    {
      "sport": "NFL",
      "team": "NEW ENGLAND PATRIOTS",
      "impliedNextGameWinProb": 0.8524590163934427
    },
    {
      "sport": "NFL",
      "team": "NEW YORK JETS",
      "impliedNextGameWinProb": 0.1475409836065574
    },
    {
      "sport": "NFL",
      "team": "MIAMI DOLPHINS",
      "impliedNextGameWinProb": 0.5720596355604638
    },
    {
      "sport": "NFL",
      "team": "WASHINGTON COMMANDERS",
      "impliedNextGameWinProb": 0.42794036443953615
    },
    {
      "sport": "NFL",
      "team": "ATLANTA FALCONS",
      "impliedNextGameWinProb": 0.6309403437815976
    },
    {
      "sport": "NFL",
      "team": "CAROLINA PANTHERS",
      "impliedNextGameWinProb": 0.3690596562184025
    },
    {
      "sport": "NFL",
      "team": "BUFFALO BILLS",
      "impliedNextGameWinProb": 0.6805555555555556
    },
    {
      "sport": "NFL",
      "team": "TAMPA BAY BUCCANEERS",
      "impliedNextGameWinProb": 0.3194444444444444
    },
    {
      "sport": "NFL",
      "team": "MINNESOTA VIKINGS",
      "impliedNextGameWinProb": 0.5996387718242023
    },
    {
      "sport": "NFL",
      "team": "CHICAGO BEARS",
      "impliedNextGameWinProb": 0.4003612281757977
    },
    {
      "sport": "NFL",
      "team": "PITTSBURGH STEELERS",
      "impliedNextGameWinProb": 0.6636481241914618
    },
    {
      "sport": "NFL",
      "team": "CINCINNATI BENGALS",
      "impliedNextGameWinProb": 0.33635187580853815
    },
    {
      "sport": "NFL",
      "team": "NEW YORK GIANTS",
      "impliedNextGameWinProb": 0.23409789548356585
    },
    {
      "sport": "NFL",
      "team": "GREEN BAY PACKERS",
      "impliedNextGameWinProb": 0.7659021045164341
    },
    {
      "sport": "NFL",
      "team": "TENNESSEE TITANS",
      "impliedNextGameWinProb": 0.2428115015974441
    },
    {
      "sport": "NFL",
      "team": "HOUSTON TEXANS",
      "impliedNextGameWinProb": 0.7571884984025559
    },
    {
      "sport": "NFL",
      "team": "JACKSONVILLE JAGUARS",
      "impliedNextGameWinProb": 0.42794036443953615
    },
    {
      "sport": "NFL",
      "team": "LOS ANGELES CHARGERS",
      "impliedNextGameWinProb": 0.5720596355604638
    },
    {
      "sport": "NFL",
      "team": "ARIZONA CARDINALS",
      "impliedNextGameWinProb": 0.42794036443953615
    },
    {
      "sport": "NFL",
      "team": "SAN FRANCISCO 49ERS",
      "impliedNextGameWinProb": 0.5720596355604638
    },
    {
      "sport": "NFL",
      "team": "LOS ANGELES RAMS",
      "impliedNextGameWinProb": 0.5720596355604638
    },
    {
      "sport": "NFL",
      "team": "SEATTLE SEAHAWKS",
      "impliedNextGameWinProb": 0.42794036443953615
    },
    {
      "sport": "NFL",
      "team": "CLEVELAND BROWNS",
      "impliedNextGameWinProb": 0.20863836017569545
    },
    {
      "sport": "NFL",
      "team": "BALTIMORE RAVENS",
      "impliedNextGameWinProb": 0.7913616398243045
    },
    {
      "sport": "NFL",
      "team": "DENVER BRONCOS",
      "impliedNextGameWinProb": 0.3775334481388264
    },
    {
      "sport": "NFL",
      "team": "KANSAS CITY CHIEFS",
      "impliedNextGameWinProb": 0.6224665518611737
    },
    {
      "sport": "NFL",
      "team": "PHILADELPHIA EAGLES",
      "impliedNextGameWinProb": 0.5260865852617197
    },
    {
      "sport": "NFL",
      "team": "DETROIT LIONS",
      "impliedNextGameWinProb": 0.4739134147382802
    },
    {
      "sport": "NFL",
      "team": "LAS VEGAS RAIDERS",
      "impliedNextGameWinProb": 0.3690596562184025
    },
    {
      "sport": "NFL",
      "team": "DALLAS COWBOYS",
      "impliedNextGameWinProb": 0.6309403437815976
    }
  ],
  "nflFutures": {
    "KANSAS CITY CHIEFS": {
      "sb": 0.13127885023384717,
      "div": 0.39573980700114536,
      "reach_sb": 0.2291621173896806
    },
    "LOS ANGELES RAMS": {
      "sb": 0.09845913767538537,
      "reach_sb": 0.17797669101128386,
      "div": 0.4681427833592549
    },
    "DETROIT LIONS": {
      "sb": 0.09266742369448035,
      "reach_sb": 0.17797669101128386,
      "div": 0.5311901022468669
    },
    "PHILADELPHIA EAGLES": {
      "sb": 0.09266742369448035,
      "reach_sb": 0.17797669101128386,
      "div": 0.9442850422274618
    },
    "SEATTLE SEAHAWKS": {
      "sb": 0.08291295804242979,
      "reach_sb": 0.16102652996259015,
      "div": 0.456724666691956
    },
    "BUFFALO BILLS": {
      "sb": 0.0787673101403083,
      "div": 0.3350696454064899,
      "reach_sb": 0.18091746109711626
    },
    "INDIANAPOLIS COLTS": {
      "sb": 0.07160664558209846,
      "div": 0.7797908106088905,
      "reach_sb": 0.15624689822023677
    },
    "GREEN BAY PACKERS": {
      "sb": 0.06059023856946793,
      "reach_sb": 0.12076989747194262,
      "div": 0.33624154620340396
    },
    "BALTIMORE RAVENS": {
      "sb": 0.05251154009353887,
      "div": 0.6753793371768118,
      "reach_sb": 0.10741974252641277
    },
    "DENVER BRONCOS": {
      "sb": 0.041456479021214895,
      "div": 0.39573980700114536,
      "reach_sb": 0.08593579402113023
    },
    "NEW ENGLAND PATRIOTS": {
      "sb": 0.041456479021214895,
      "div": 0.6611181849751128,
      "reach_sb": 0.10110093414250615
    },
    "LOS ANGELES CHARGERS": {
      "sb": 0.030295119284733964,
      "div": 0.20666412143393145,
      "reach_sb": 0.06610445693933094
    },
    "TAMPA BAY BUCCANEERS": {
      "sb": 0.030295119284733964,
      "reach_sb": 0.06502994479258449,
      "div": 0.8554615266216861
    },
    "SAN FRANCISCO 49ERS": {
      "sb": 0.019211539058611782,
      "reach_sb": 0.03675605575233036,
      "div": 0.07202196667065461
    },
    "JACKSONVILLE JAGUARS": {
      "sb": 0.015444570615746726,
      "div": 0.1559581621217781,
      "reach_sb": 0.023871053894758396
    },
    "CHICAGO BEARS": {
      "sb": 0.010364119755303724,
      "reach_sb": 0.020619250787892646,
      "div": 0.1027404724510401
    },
    "PITTSBURGH STEELERS": {
      "sb": 0.010364119755303724,
      "div": 0.2701517348707247,
      "reach_sb": 0.01685015569041769
    },
    "HOUSTON TEXANS": {
      "sb": 0.010364119755303724,
      "div": 0.06238326484871124,
      "reach_sb": 0.020959949761251276
    },
    "MINNESOTA VIKINGS": {
      "sb": 0.005216378154987305,
      "reach_sb": 0.013858840693501613,
      "div": 0.029827879098689062
    },
    "CINCINNATI BENGALS": {
      "sb": 0.003918771648771557,
      "div": 0.049764793265659815,
      "reach_sb": 0.0028550097681438614
    },
    "DALLAS COWBOYS": {
      "sb": 0.003918771648771557,
      "reach_sb": 0.008370190913897013,
      "div": 0.04222889629837096
    },
    "CAROLINA PANTHERS": {
      "sb": 0.003918771648771557,
      "reach_sb": 0.011123543188205241,
      "div": 0.10005397972183462
    },
    "ATLANTA FALCONS": {
      "sb": 0.0026168541574853256,
      "reach_sb": 0.008370190913897013,
      "div": 0.041326643798149085
    },
    "ARIZONA CARDINALS": {
      "sb": 0.0026168541574853256,
      "reach_sb": 0.008370190913897013,
      "div": 0.0031105832781345845
    },
    "WASHINGTON COMMANDERS": {
      "sb": 0.0015722017992077504,
      "reach_sb": 0.005598604518566877,
      "div": 0.009616481335272596
    },
    "CLEVELAND BROWNS": {
      "sb": 0.0007868862151878952,
      "div": 0.004704134686803664,
      "reach_sb": 0.0017152853098029983
    },
    "TENNESSEE TITANS": {
      "sb": 0.0007868862151878952,
      "div": 0.001867762420620097,
      "reach_sb": 0.0017152853098029983
    },
    "LAS VEGAS RAIDERS": {
      "sb": 0.0007868862151878952,
      "div": 0.0018562645637778272,
      "reach_sb": 0.0017152853098029983
    },
    "MIAMI DOLPHINS": {
      "sb": 0.0007868862151878952,
      "div": 0.0019060848091985952,
      "reach_sb": 0.0017152853098029983
    },
    "NEW ORLEANS SAINTS": {
      "sb": 0.0007868862151878952,
      "reach_sb": 0.0028086022667893635,
      "div": 0.003157849858330329
    },
    "NEW YORK GIANTS": {
      "sb": 0.0007868862151878952,
      "reach_sb": 0.003368084790054177,
      "div": 0.0038695801388945504
    },
    "NEW YORK JETS": {
      "sb": 0.0007868862151878952,
      "div": 0.0019060848091985952,
      "reach_sb": 0.0017152853098029983
    }
  },
  "nflCurrentOU": {
    "ARIZONA CARDINALS": 6.5,
    "ATLANTA FALCONS": 9.5,
    "BALTIMORE RAVENS": 8.5,
    "BUFFALO BILLS": 11.5,
    "CAROLINA PANTHERS": 6.5,
    "CHICAGO BEARS": 8.5,
    "CINCINNATI BENGALS": 5.5,
    "CLEVELAND BROWNS": 5.5,
    "DALLAS COWBOYS": 6.5,
    "DENVER BRONCOS": 10.5,
    "DETROIT LIONS": 10.5,
    "GREEN BAY PACKERS": 11.5,
    "HOUSTON TEXANS": 8.5,
    "INDIANAPOLIS COLTS": 11.5,
    "JACKSONVILLE JAGUARS": 9.5,
    "KANSAS CITY CHIEFS": 10.5,
    "LOS ANGELES CHARGERS": 10.5,
    "LOS ANGELES RAMS": 10.5,
    "LAS VEGAS RAIDERS": 7.5,
    "MIAMI DOLPHINS": 5.5,
    "MINNESOTA VIKINGS": 8.5,
    "NEW ENGLAND PATRIOTS": 10.5,
    "NEW ORLEANS SAINTS": 4.5,
    "NEW YORK GIANTS": 5.5,
    "NEW YORK JETS": 4.5,
    "PHILADELPHIA EAGLES": 10.5,
    "PITTSBURGH STEELERS": 9.5,
    "SAN FRANCISCO 49ERS": 10.5,
    "SEATTLE SEAHAWKS": 10.5,
    "TAMPA BAY BUCCANEERS": 11.5,
    "TENNESSEE TITANS": 3.5,
    "WASHINGTON COMMANDERS": 8.5
  }
}